mqbeebotte/__init__.py
mqbeebotte/client.py
mqbeebotte-0.0.4.dist-info/LICENSE.txt
mqbeebotte-0.0.4.dist-info/METADATA
mqbeebotte-0.0.4.dist-info/WHEEL
mqbeebotte-0.0.4.dist-info/top_level.txt
mqbeebotte-0.0.4.dist-info/RECORD
