Metadata-Version: 2.1
Name: mqbeebotte
Version: 0.0.4
Summary: Unofficial Beebotte MQTT access package
Home-page: https://github.com/pman0214/mqbeebotte
Author: Shigemi ISHIDA
Author-email: ishida+devel@f.ait.kyushu-u.ac.jp
License: UNKNOWN
Project-URL: Bug Reports, https://github.com/pman0214/mqbeebotte/issues
Project-URL: Source, https://github.com/pman0214/mqbeebotte/
Keywords: mqtt beebotte
Platform: UNKNOWN
Classifier: Development Status :: 3 - Alpha
Classifier: Intended Audience :: Developers
Classifier: Topic :: Communications
Classifier: Topic :: Internet :: WWW/HTTP
Classifier: Topic :: Software Development :: Libraries :: Python Modules
Classifier: License :: OSI Approved :: BSD License
Classifier: Programming Language :: Python :: 3
Classifier: Programming Language :: Python :: 3.5
Classifier: Programming Language :: Python :: 3.6
Classifier: Programming Language :: Python :: 3.7
Classifier: Programming Language :: Python :: 3.8
Requires-Python: !=3.0.*, !=3.1.*, !=3.2.*, !=3.3.*, !=3.4.*, <4
Requires-Dist: paho-mqtt
